vlibras_translate/ConverteExtenso.py
vlibras_translate/Iterator.py
vlibras_translate/__init__.py
vlibras_translate/aelius_tagger.py
vlibras_translate/cfg.syn.nltk
vlibras_translate/char_preprocessing.py
vlibras_translate/dExtenso.py
vlibras_translate/errors_orto.txt
vlibras_translate/exceptions.py
vlibras_translate/expressoes_com_palavras_removiveis
vlibras_translate/famosos
vlibras_translate/file_translation.py
vlibras_translate/health_check.py
vlibras_translate/lemma.py
vlibras_translate/lista_branca
vlibras_translate/lugares
vlibras_translate/name_checking.py
vlibras_translate/number.py
vlibras_translate/orthography.py
vlibras_translate/palavras_compostas_e_sinonimos
vlibras_translate/postprocessing.py
vlibras_translate/pygtrie_CharTrie_names_pickle_wout_inter_3
vlibras_translate/replace_cardinals.py
vlibras_translate/singleton.py
vlibras_translate/translation.py
vlibras_translate/utils.py
vlibras_translate/word_processing.py
vlibras_translate/aelius/__init__.py
vlibras_translate/aelius/Aelius/AnotaCorpus.py
vlibras_translate/aelius/Aelius/AnotaTextosLXTagger.py
vlibras_translate/aelius/Aelius/Avalia.py
vlibras_translate/aelius/Aelius/CalculaEstatisticasLexicais.py
vlibras_translate/aelius/Aelius/Chunking.py
vlibras_translate/aelius/Aelius/ConstroiBRUBT.py
vlibras_translate/aelius/Aelius/ConstroiRUBT.py
vlibras_translate/aelius/Aelius/CorrigeTexto.py
vlibras_translate/aelius/Aelius/ExpandeContracoes.py
vlibras_translate/aelius/Aelius/Extras.py
vlibras_translate/aelius/Aelius/MXPOST.py
vlibras_translate/aelius/Aelius/ProcessaCorpus.py
vlibras_translate/aelius/Aelius/ProcessaNomesProprios.py
vlibras_translate/aelius/Aelius/SimplificaEtiquetas.py
vlibras_translate/aelius/Aelius/Toqueniza.py
vlibras_translate/aelius/Aelius/__init__.py
vlibras_translate/aelius/Aelius/openNLP.py
vlibras_translate/aelius/Aelius/openNLPJava.py
vlibras_translate/aelius/aelius_data/AeliusHunPos
vlibras_translate/aelius/aelius_data/LICENSE.txt
vlibras_translate/aelius/bin/hunpos-tag
vlibras_translate-1.1.10.dist-info/LICENSE
vlibras_translate-1.1.10.dist-info/METADATA
vlibras_translate-1.1.10.dist-info/WHEEL
vlibras_translate-1.1.10.dist-info/entry_points.txt
vlibras_translate-1.1.10.dist-info/top_level.txt
vlibras_translate-1.1.10.dist-info/RECORD
