Metadata-Version: 2.1
Name: vlibras-translate
Version: 1.1.10
Summary: VLibras (LAVID-UFPB) translation module for translating brazilian portuguese to LIBRAS.
Home-page: http://www.vlibras.gov.br/
Author: MoraesCaio (LAVID-UFPB)
Author-email: caiomoraes.cesar@gmail.com
License: UNKNOWN
Platform: UNKNOWN
Classifier: License :: OSI Approved :: GNU Lesser General Public License v3 (LGPLv3)
Classifier: Operating System :: POSIX :: Linux
Classifier: Operating System :: Microsoft :: Windows
Classifier: Programming Language :: Python :: 3
Classifier: Programming Language :: Python :: 3.5
Classifier: Programming Language :: Python :: 3.6
Classifier: Development Status :: 5 - Production/Stable
Classifier: Topic :: Text Processing :: Linguistic
Classifier: Natural Language :: Portuguese (Brazilian)
Requires-Dist: nltk
Requires-Dist: unidecode
Requires-Dist: pygtrie
Requires-Dist: pyjnius
Requires-Dist: pyparsing
Requires-Dist: psutil
Requires-Dist: interruptingcow
Requires-Dist: hunspell ; platform_system == "Linux"
Provides-Extra: deeplearning
Requires-Dist: vlibras-deeplearning ; extra == 'deeplearning'
